{
  "site": "hesport.com",
  "siteName": "Hesport",
  "siteNameAr": "هسبورت",
  "widgetTitle": "فلاش رياضي",
  "widgetCategoryUrl": "https://www.hesport.com/akhbar",
  "sourceUrl": "https://www.hesport.com/",
  "fetchedAt": "2026-03-30T22:15:58.924Z",
  "fetchedDate": "2026-03-30",
  "fetchedAtLocaleAr": "الاثنين، 30 مارس 2026 في 23:15",
  "count": 16,
  "articles": [
    {
      "url": "https://www.hesport.com/%d8%ad%d8%b3%d8%a7%d9%85-%d8%ad%d8%b3%d9%86-%d9%85%d9%86%d8%aa%d8%ae%d8%a8-%d9%85%d8%b5%d8%b1-%d9%84%d8%a7-%d9%8a%d8%ae%d8%b4%d9%89-%d8%a3%d8%ad%d8%af%d8%a7-433020.html",
      "title": "حسام حسن: منتخب مصر لا يخشى أحدا",
      "timeLabel": "22:26",
      "headline": "حسام حسن: منتخب مصر لا يخشى أحدا",
      "slug": "حسام-حسن-منتخب-مصر-لا-يخشى-أحدا-433020",
      "articleId": "433020"
    },
    {
      "url": "https://www.hesport.com/%d8%a7%d9%84%d8%ac%d9%8a%d8%b4-%d8%a7%d9%84%d9%85%d9%84%d9%83%d9%8a-%d9%8a%d8%b7%d8%b1%d8%ad-%d8%aa%d8%b0%d8%a7%d9%83%d8%b1-%d9%85%d9%88%d8%a7%d8%ac%d9%87%d8%a9-%d8%a7%d9%84%d8%af%d8%b4%d9%8a%d8%b1-433015.html",
      "title": "الجيش الملكي يطرح تذاكر مواجهة الدشيرة",
      "timeLabel": "21:34",
      "headline": "الجيش الملكي يطرح تذاكر مواجهة الدشيرة",
      "slug": "الجيش-الملكي-يطرح-تذاكر-مواجهة-الدشير-433015",
      "articleId": "433015"
    },
    {
      "url": "https://www.hesport.com/%d8%a7%d9%84%d8%a8%d8%a7%d8%ac%d9%88%d9%81%d9%8a-%d9%8a%d9%86%d8%a7%d9%84-%d8%ac%d8%a7%d8%a6%d8%b2%d8%a9-%d8%a7%d9%84%d8%a3%d9%81%d8%b6%d9%84-%d8%a3%d9%85%d8%a7%d9%85-%d9%85%d8%b5%d8%b1-432992.html",
      "title": "الباجوفي ينال جائزة \"الأفضل\" أمام مصر",
      "timeLabel": "20:08",
      "headline": "الباجوفي ينال جائزة \"الأفضل\" أمام مصر",
      "slug": "الباجوفي-ينال-جائزة-الأفضل-أمام-مصر-432992",
      "articleId": "432992"
    },
    {
      "url": "https://www.hesport.com/%d8%a7%d9%84%d8%a7%d8%aa%d8%ad%d8%a7%d8%af-%d8%a7%d9%84%d9%84%d9%8a%d8%a8%d9%8a-%d9%8a%d9%81%d9%88%d8%b2-%d8%b9%d9%84%d9%89-%d8%a7%d9%84%d9%88%d8%af%d8%a7%d8%af-%d8%a8%d8%ab%d9%84%d8%a7%d8%ab%d9%8a-432996.html",
      "title": "الاتحاد الليبي يفوز على الوداد بثلاثية",
      "timeLabel": "19:23",
      "headline": "الاتحاد الليبي يفوز على الوداد بثلاثية",
      "slug": "الاتحاد-الليبي-يفوز-على-الوداد-بثلاثي-432996",
      "articleId": "432996"
    },
    {
      "url": "https://www.hesport.com/%d8%a3%d9%88%d9%84%d9%85%d8%a8%d9%8a%d9%83-%d8%a7%d9%84%d8%af%d8%b4%d9%8a%d8%b1%d8%a9-%d9%8a%d9%86%d9%81%d8%b5%d9%84-%d8%b9%d9%86-%d8%a7%d9%84%d9%85%d8%af%d8%b1%d8%a8-%d9%88%d9%85%d8%b3%d8%a7%d8%b9-432983.html",
      "title": "أولمبيك الدشيرة ينفصل عن المدرب ومساعده",
      "timeLabel": "18:08",
      "headline": "أولمبيك الدشيرة ينفصل عن المدرب ومساعده",
      "slug": "أولمبيك-الدشيرة-ينفصل-عن-المدرب-ومساع-432983",
      "articleId": "432983"
    },
    {
      "url": "https://www.hesport.com/%d8%b3%d9%8a%d8%a7%d9%85%d8%a8%d8%b1%d9%8a-%d8%a8%d8%a7%d9%84%d9%88%d9%85%d8%a7-%d8%aa%d9%86%d8%aa%d9%82%d8%af-%d8%a3%d8%af%d8%a7%d8%a1-%d8%a7%d9%84%d9%85%d8%ba%d8%b1%d8%a8-%d8%a7-432977.html",
      "title": "“سيامبري بالوما” تنتقد أداء المغرب التطواني",
      "timeLabel": "17:06",
      "headline": "“سيامبري بالوما” تنتقد أداء المغرب التطواني",
      "slug": "سيامبري-بالوما-تنتقد-أداء-المغرب-ا-432977",
      "articleId": "432977"
    },
    {
      "url": "https://www.hesport.com/%d8%a7%d9%84%d8%b4%d8%a7%d8%b1%d9%83-%d9%8a%d8%b7%d8%a7%d9%84%d8%a8-%d8%a8%d8%a7%d9%84%d8%a5%d9%81%d8%b1%d8%a7%d8%ac-%d8%b9%d9%86-%d8%a7%d9%84%d9%85%d8%b9%d8%aa%d9%82%d9%84%d9%8a%d9%86-432966.html",
      "title": "\"الشارك\" يطالب بالإفراج عن المعتقلين",
      "timeLabel": "16:20",
      "headline": "\"الشارك\" يطالب بالإفراج عن المعتقلين",
      "slug": "الشارك-يطالب-بالإفراج-عن-المعتقلين-432966",
      "articleId": "432966"
    },
    {
      "url": "https://www.hesport.com/%d8%a7%d9%84%d9%87%d9%84%d8%a7%d9%84-%d8%a7%d9%84%d8%b3%d9%88%d8%af%d8%a7%d9%86%d9%8a-%d9%8a%d8%b4%d8%aa%d9%83%d9%8a-%d8%a8%d8%b3%d8%a8%d8%a8-%d9%85%d8%b4%d8%a7%d8%b1%d9%83%d8%a9-%d8%a7%d9%84%d9%85-432957.html",
      "title": "الهلال السوداني يشتكي بسبب مشاركة الموساوي",
      "timeLabel": "15:17",
      "headline": "الهلال السوداني يشتكي بسبب مشاركة الموساوي",
      "slug": "الهلال-السوداني-يشتكي-بسبب-مشاركة-الم-432957",
      "articleId": "432957"
    },
    {
      "url": "https://www.hesport.com/%d9%85%d8%af%d8%b1%d8%a8-%d8%a8%d8%a7%d8%b1%d8%a7%d8%ba%d9%88%d8%a7%d9%8a-%d9%8a%d8%b4%d9%8a%d8%af-%d8%a8%d8%a7%d9%84%d9%83%d8%b1%d8%a9-%d8%a7%d9%84%d9%85%d8%ba%d8%b1%d8%a8%d9%8a%d8%a9-432942.html",
      "title": "مدرب باراغواي يشيد بالكرة المغربية",
      "timeLabel": "14:25",
      "headline": "مدرب باراغواي يشيد بالكرة المغربية",
      "slug": "مدرب-باراغواي-يشيد-بالكرة-المغربية-432942",
      "articleId": "432942"
    },
    {
      "url": "https://www.hesport.com/%d8%a7%d9%84%d8%a8%d8%a7%d8%b1%d8%a7%d8%ba%d9%88%d8%a7%d9%8a-%d8%ae%d8%b5%d9%85-%d9%85%d9%86%d8%b8%d9%85-%d9%8a%d8%ae%d8%aa%d8%a8%d8%b1-%d8%ac%d8%a7%d9%87%d8%b2%d9%8a%d8%a9-%d8%a7%d9%84%d8%a3%d8%b3-432945.html",
      "title": "باراغواي خصم منظم يختبر جاهزية \"الأسود\"",
      "timeLabel": "13:23",
      "headline": "باراغواي خصم منظم يختبر جاهزية \"الأسود\"",
      "slug": "الباراغواي-خصم-منظم-يختبر-جاهزية-الأس-432945",
      "articleId": "432945"
    },
    {
      "url": "https://www.hesport.com/%d8%b3%d8%a8%d8%a7%d9%82-%d8%b4%d8%b9%d8%a8%d9%8a-%d9%8a%d9%86%d8%a7%d9%84-%d8%a7%d9%84%d8%a5%d9%82%d8%a8%d8%a7%d9%84-%d8%a8%d9%85%d8%af%d9%8a%d9%86%d8%a9-%d9%81%d8%a7%d8%b3-432939.html",
      "title": "سباق شعبي ينال الإقبال بمدينة فاس",
      "timeLabel": "13:04",
      "headline": "سباق شعبي ينال الإقبال بمدينة فاس",
      "slug": "سباق-شعبي-ينال-الإقبال-بمدينة-فاس-432939",
      "articleId": "432939"
    },
    {
      "url": "https://www.hesport.com/%d9%85%d8%ba%d8%b1%d8%a8%d9%8a%d8%a7%d9%86-%d9%81%d9%8a-%d8%a7%d9%84%d8%a7%d8%aa%d8%ad%d8%a7%d8%af-%d8%a7%d9%84%d8%b9%d8%b1%d8%a8%d9%8a-%d9%84%d9%84%d8%aa%d8%ac%d8%af%d9%8a%d9%81-432936.html",
      "title": "مغربيان في الاتحاد العربي للتجديف",
      "timeLabel": "12:05",
      "headline": "مغربيان في الاتحاد العربي للتجديف",
      "slug": "مغربيان-في-الاتحاد-العربي-للتجديف-432936",
      "articleId": "432936"
    },
    {
      "url": "https://www.hesport.com/%d9%86%d8%aa%d8%a7%d8%a6%d8%ac-%d9%85%d8%ae%d9%8a%d8%a8%d8%a9-%d9%84%d9%84%d8%aa%d9%86%d8%b3-%d8%a7%d9%84%d9%85%d8%ba%d8%b1%d8%a8%d9%8a-%d8%a8%d9%85%d8%b1%d8%a7%d9%83%d8%b4-432933.html",
      "title": "نتائج مخيبة للتنس المغربي بمراكش",
      "timeLabel": "11:04",
      "headline": "نتائج مخيبة للتنس المغربي بمراكش",
      "slug": "نتائج-مخيبة-للتنس-المغربي-بمراكش-432933",
      "articleId": "432933"
    },
    {
      "url": "https://www.hesport.com/%d8%ad%d9%83%d9%8a%d9%85%d9%8a-%d9%8a%d8%b7%d8%a7%d8%b1%d8%af-%d8%b1%d9%82%d9%85-%d8%a7%d9%84%d9%86%d9%8a%d8%a8%d8%aa-%d8%a7%d9%84%d8%aa%d8%a7%d8%b1%d9%8a%d8%ae%d9%8a-432923.html",
      "title": "حكيمي يطارد رقم النيبت التاريخي",
      "timeLabel": "10:08",
      "headline": "حكيمي يطارد رقم النيبت التاريخي",
      "slug": "حكيمي-يطارد-رقم-النيبت-التاريخي-432923",
      "articleId": "432923"
    },
    {
      "url": "https://www.hesport.com/%d9%86%d8%aa%d8%a7%d8%a6%d8%ac-%d8%a7%d9%84%d9%82%d8%b3%d9%85-%d8%a7%d9%84%d8%ab%d8%a7%d9%86%d9%8a-%d9%84%d9%83%d8%b1%d8%a9-%d8%a7%d9%84%d9%82%d8%af%d9%85-%d8%a8%d8%a7%d9%84%d9%85%d8%ba%d8%b1%d8%a8-4-432911.html",
      "title": "نتائج القسم الثاني لكرة القدم بالمغرب",
      "timeLabel": "09:00",
      "headline": "نتائج القسم الثاني لكرة القدم بالمغرب",
      "slug": "نتائج-القسم-الثاني-لكرة-القدم-بالمغرب-4-432911",
      "articleId": "432911"
    },
    {
      "url": "https://www.hesport.com/%d8%a7%d9%86%d8%b7%d9%84%d8%a7%d9%82-%d8%b1%d8%a7%d9%84%d9%8a-%d8%b9%d8%a7%d8%a6%d8%b4%d8%a9-%d9%84%d9%84%d8%ba%d8%b2%d8%a7%d9%84%d8%a7%d8%aa-%d9%86%d8%ad%d9%88-%d8%a7%d9%84%d8%b5%d8%ad%d8%b1%d8%a7-432870.html",
      "title": "انطلاق رالي عائشة للغزالات نحو الصحراء",
      "timeLabel": "23:17",
      "headline": "انطلاق رالي عائشة للغزالات نحو الصحراء",
      "slug": "انطلاق-رالي-عائشة-للغزالات-نحو-الصحرا-432870",
      "articleId": "432870"
    }
  ]
}